MANIFEST.in
README.md
setup.py
museumghosts/__init__.py
museumghosts/forgetlist.py
museumghosts/game.py
museumghosts/gameobjects.py
museumghosts/geometry.py
museumghosts/graphics.py
museumghosts/mazegen.py
museumghosts/preprocessor.py
museumghosts/sprites.py
museumghosts/util.py
museumghosts.egg-info/PKG-INFO
museumghosts.egg-info/SOURCES.txt
museumghosts.egg-info/dependency_links.txt
museumghosts.egg-info/entry_points.txt
museumghosts.egg-info/requires.txt
museumghosts.egg-info/top_level.txt
museumghosts/assets/floor.png
museumghosts/assets/g1.png
museumghosts/assets/g_dead.png
museumghosts/assets/ghost-screenshot.png
museumghosts/assets/ghost.png
museumghosts/assets/guard.png