Metadata-Version: 2.1
Name: museumghosts
Version: 0.1.2
Summary: UNKNOWN
Home-page: UNKNOWN
Author: pgdr
License: UNKNOWN
Platform: UNKNOWN
